[{"bbox": [789, 0, 802, 18], "text": "\\", "line_num": 1, "block_num": 1}, {"bbox": [49, 26, 168, 52], "text": "Operating", "line_num": 1, "block_num": 2}, {"bbox": [178, 27, 314, 46], "text": "Parameters", "line_num": 1, "block_num": 2}, {"bbox": [795, 47, 801, 59], "text": "\u2018", "line_num": 1, "block_num": 2}, {"bbox": [50, 70, 88, 88], "text": "Max.", "line_num": 1, "block_num": 3}, {"bbox": [95, 69, 158, 89], "text": "System", "line_num": 1, "block_num": 3}, {"bbox": [164, 68, 231, 89], "text": "Voltage", "line_num": 1, "block_num": 3}, {"bbox": [350, 69, 373, 84], "text": "DC", "line_num": 1, "block_num": 3}, {"bbox": [379, 68, 472, 88], "text": "1500V(IEC)", "line_num": 1, "block_num": 3}, {"bbox": [49, 106, 138, 126], "text": "Operating", "line_num": 2, "block_num": 3}, {"bbox": [142, 105, 260, 126], "text": "Temperature", "line_num": 2, "block_num": 3}, {"bbox": [348, 97, 395, 120], "text": "-40\u00b0C", "line_num": 2, "block_num": 3}, {"bbox": [404, 109, 410, 114], "text": "~", "line_num": 2, "block_num": 3}, {"bbox": [414, 97, 465, 120], "text": "+85\u00b0C", "line_num": 2, "block_num": 3}, {"bbox": [751, 100, 752, 128], "text": "|", "line_num": 2, "block_num": 3}, {"bbox": [50, 140, 88, 154], "text": "Max.", "line_num": 3, "block_num": 3}, {"bbox": [95, 140, 135, 154], "text": "Fuse", "line_num": 3, "block_num": 3}, {"bbox": [142, 139, 198, 159], "text": "Rating", "line_num": 3, "block_num": 3}, {"bbox": [347, 139, 381, 154], "text": "25A", "line_num": 3, "block_num": 3}, {"bbox": [23, 171, 24, 176], "text": "__", "line_num": 4, "block_num": 3}, {"bbox": [50, 174, 89, 194], "text": "Frontside", "line_num": 4, "block_num": 3}, {"bbox": [145, 166, 178, 194], "text": "Max.", "line_num": 4, "block_num": 3}, {"bbox": [181, 166, 256, 194], "text": "Loading", "line_num": 4, "block_num": 3}, {"bbox": [348, 166, 412, 194], "text": "5400Pa", "line_num": 4, "block_num": 3}, {"bbox": [744, 166, 752, 193], "text": "]", "line_num": 4, "block_num": 3}, {"bbox": [789, 140, 802, 202], "text": "(", "line_num": 4, "block_num": 3}, {"bbox": [53, 209, 131, 225], "text": "Backside", "line_num": 5, "block_num": 3}, {"bbox": [138, 211, 176, 225], "text": "Max.", "line_num": 5, "block_num": 3}, {"bbox": [184, 209, 254, 230], "text": "Loading", "line_num": 5, "block_num": 3}, {"bbox": [348, 213, 412, 228], "text": "2400Pa", "line_num": 5, "block_num": 3}, {"bbox": [52, 250, 86, 265], "text": "Fire", "line_num": 1, "block_num": 4}, {"bbox": [96, 249, 185, 268], "text": "Resistance", "line_num": 1, "block_num": 4}, {"bbox": [349, 249, 378, 264], "text": "IEC", "line_num": 1, "block_num": 4}, {"bbox": [382, 248, 444, 264], "text": "Class", "line_num": 1, "block_num": 4}, {"bbox": [438, 242, 447, 278], "text": "C", "line_num": 1, "block_num": 4}, {"bbox": [751, 244, 752, 272], "text": "|", "line_num": 1, "block_num": 4}]