[{"bbox": [20, 18, 51, 33], "text": "Cell", "line_num": 1, "block_num": 4}, {"bbox": [58, 19, 97, 37], "text": "Type", "line_num": 1, "block_num": 4}, {"bbox": [307, 19, 356, 33], "text": "N-IBC", "line_num": 1, "block_num": 5}, {"bbox": [364, 18, 549, 36], "text": "166x83mm(Half-Cell}", "line_num": 1, "block_num": 5}, {"bbox": [20, 49, 44, 63], "text": "No.", "line_num": 1, "block_num": 7}, {"bbox": [56, 48, 72, 63], "text": "of", "line_num": 1, "block_num": 7}, {"bbox": [79, 44, 119, 73], "text": "Cells", "line_num": 1, "block_num": 7}, {"bbox": [386, 49, 468, 66], "text": "120(6x20)", "line_num": 1, "block_num": 8}, {"bbox": [19, 80, 92, 94], "text": "Junction", "line_num": 1, "block_num": 10}, {"bbox": [100, 79, 130, 93], "text": "Box", "line_num": 1, "block_num": 10}, {"bbox": [298, 79, 334, 98], "text": "Ip68", "line_num": 1, "block_num": 11}, {"bbox": [340, 81, 375, 93], "text": "with", "line_num": 1, "block_num": 11}, {"bbox": [383, 79, 427, 93], "text": "three", "line_num": 1, "block_num": 11}, {"bbox": [435, 79, 493, 98], "text": "bypass", "line_num": 1, "block_num": 11}, {"bbox": [500, 79, 558, 93], "text": "diodes", "line_num": 1, "block_num": 11}, {"bbox": [20, 123, 82, 137], "text": "Output", "line_num": 1, "block_num": 13}, {"bbox": [89, 122, 137, 137], "text": "Cable", "line_num": 1, "block_num": 13}, {"bbox": [317, 107, 370, 126], "text": "4mm?,", "line_num": 1, "block_num": 14}, {"bbox": [377, 110, 449, 124], "text": "1200mm", "line_num": 1, "block_num": 14}, {"bbox": [457, 110, 491, 124], "text": "with", "line_num": 1, "block_num": 14}, {"bbox": [500, 110, 538, 124], "text": "MC4", "line_num": 1, "block_num": 14}, {"bbox": [314, 136, 379, 154], "text": "(Length", "line_num": 2, "block_num": 14}, {"bbox": [386, 140, 415, 150], "text": "can", "line_num": 2, "block_num": 14}, {"bbox": [423, 135, 443, 150], "text": "be", "line_num": 2, "block_num": 14}, {"bbox": [450, 136, 541, 153], "text": "customed)", "line_num": 2, "block_num": 14}, {"bbox": [20, 168, 64, 182], "text": "Glass", "line_num": 1, "block_num": 19}, {"bbox": [294, 168, 353, 182], "text": "3.2mm", "line_num": 1, "block_num": 19}, {"bbox": [360, 168, 419, 182], "text": "coated", "line_num": 1, "block_num": 19}, {"bbox": [426, 167, 511, 186], "text": "tempered", "line_num": 1, "block_num": 19}, {"bbox": [519, 168, 561, 187], "text": "glass", "line_num": 1, "block_num": 19}, {"bbox": [20, 203, 72, 217], "text": "Frame", "line_num": 2, "block_num": 19}, {"bbox": [287, 202, 370, 217], "text": "Anodized", "line_num": 2, "block_num": 19}, {"bbox": [378, 202, 464, 217], "text": "aluminum", "line_num": 2, "block_num": 19}, {"bbox": [472, 202, 512, 221], "text": "alloy", "line_num": 2, "block_num": 19}, {"bbox": [518, 202, 568, 217], "text": "frame", "line_num": 2, "block_num": 19}, {"bbox": [21, 234, 112, 261], "text": "Dimension", "line_num": 3, "block_num": 19}, {"bbox": [350, 238, 504, 252], "text": "1727x1039x30mm.", "line_num": 3, "block_num": 19}, {"bbox": [19, 267, 82, 294], "text": "Weight", "line_num": 4, "block_num": 19}, {"bbox": [399, 271, 456, 290], "text": "20.0kg", "line_num": 4, "block_num": 19}]